README.md
setup.cfg
setup.py
haproxy_pygments_lexer.egg-info/PKG-INFO
haproxy_pygments_lexer.egg-info/SOURCES.txt
haproxy_pygments_lexer.egg-info/dependency_links.txt
haproxy_pygments_lexer.egg-info/entry_points.txt
haproxy_pygments_lexer.egg-info/requires.txt
haproxy_pygments_lexer.egg-info/top_level.txt
haproxylexer/__init__.py
haproxylexer/_haproxy_builtins.py
haproxylexer/lexer.py