Metadata-Version: 2.1
Name: haproxy-pygments-lexer
Version: 1.0.0
Summary: A Pygments Lexer for the HAProxy configuration syntax
Home-page: https://github.com/haproxytech/haproxy-pygments-lexer
Author: HAProxy Technologies
Author-email: nigniatovic@haproxy.com
License: Apache Software License
Keywords: haproxy,syntax highlighting
Platform: any
Classifier: Intended Audience :: Developers
Classifier: Intended Audience :: End Users/Desktop
Classifier: Intended Audience :: System Administrators
Classifier: Programming Language :: Python :: 3
Classifier: Programming Language :: Python :: 3.5
Classifier: Programming Language :: Python :: 3.6
Classifier: Programming Language :: Python :: 3.7
Classifier: Programming Language :: Python :: 3.8
Classifier: Programming Language :: Python :: 3.9
Classifier: License :: OSI Approved :: Apache Software License
Classifier: Operating System :: OS Independent
Classifier: Topic :: Text Processing :: Filters
Classifier: Topic :: Utilities
Requires-Python: >=3
